live_score_api_com/__init__.py
live_score_api_com/competition_standings.py
live_score_api_com/group_standings.py
live_score_api_com/history.py
live_score_api_com/live_scores.py
live_score_api_com/main.py
live_score_api_com-1.1.dist-info/METADATA
live_score_api_com-1.1.dist-info/WHEEL
live_score_api_com-1.1.dist-info/top_level.txt
live_score_api_com-1.1.dist-info/RECORD
