Metadata-Version: 2.1
Name: live-score-api-com
Version: 1.1
Summary: UNKNOWN
Home-page: UNKNOWN
License: UNKNOWN
Platform: UNKNOWN
Requires-Dist: requests
